autosrt/__init__.py
autosrt-1.4.9.dist-info/METADATA
autosrt-1.4.9.dist-info/WHEEL
autosrt-1.4.9.dist-info/entry_points.txt
autosrt-1.4.9.dist-info/top_level.txt
autosrt-1.4.9.dist-info/RECORD
