Metadata-Version: 2.1
Name: autosrt
Version: 1.4.9
Summary: a utility for automatic speech recognition and subtitle generation
Home-page: https://github.com/botbahlul/autosrt
Author: Bot Bahlul
Author-email: bot.bahlul@gmail.com
License: MIT License
Requires-Dist: requests >=2.3.0
Requires-Dist: httpx >=0.24.0
Requires-Dist: urllib3 <3.0,>=1.26.0
Requires-Dist: pysrt >=1.0.1
Requires-Dist: six >=1.11.0
Requires-Dist: progressbar2 >=3.34.3
